psipy/__init__.py
psipy/conftest.py
psipy/data/__init__.py
psipy/data/sample_data.py
psipy/io/__init__.py
psipy/io/mas.py
psipy/io/pluto.py
psipy/io/util.py
psipy/io/tests/__init__.py
psipy/io/tests/test_mas.py
psipy/io/tests/test_pluto.py
psipy/io/tests/test_util.py
psipy/model/__init__.py
psipy/model/base.py
psipy/model/mas.py
psipy/model/pluto.py
psipy/model/variable.py
psipy/model/tests/__init__.py
psipy/model/tests/test_mas.py
psipy/model/tests/test_plotting.py
psipy/model/tests/test_pluto.py
psipy/model/tests/test_variable.py
psipy/tracing/__init__.py
psipy/tracing/flines.py
psipy/tracing/tracing.py
psipy/tracing/tests/__init__.py
psipy/tracing/tests/test_tracing.py
psipy/util/__init__.py
psipy/util/decorators.py
psipy/visualization/__init__.py
psipy/visualization/matplotlib.py
psipy/visualization/pyvista.py
psipy/visualization/tests/__init__.py
psipy-0.4.0.dist-info/LICENSE
psipy-0.4.0.dist-info/METADATA
psipy-0.4.0.dist-info/WHEEL
psipy-0.4.0.dist-info/top_level.txt
psipy-0.4.0.dist-info/RECORD
